hello_world/__init__.py
hola_mundo_edison-0.1.1.dist-info/METADATA
hola_mundo_edison-0.1.1.dist-info/WHEEL
hola_mundo_edison-0.1.1.dist-info/top_level.txt
hola_mundo_edison-0.1.1.dist-info/RECORD
